djangoauthtoken/__init__.py
djangoauthtoken/asgi.py
djangoauthtoken/settings.py
djangoauthtoken/urls.py
djangoauthtoken/wsgi.py
djangoauthtoken/middleware/__init__.py
djangoauthtoken/middleware/token_authentication.py
djangoauthtoken/migrations/0001_initial.py
djangoauthtoken/migrations/0002_alter_token_refresh_token_alter_token_token.py
djangoauthtoken/migrations/0003_alter_tokenuser_email.py
djangoauthtoken/migrations/__init__.py
djangoauthtoken/models/__init__.py
djangoauthtoken/models/base_relation.py
djangoauthtoken/models/token.py
djangoauthtoken/models/token_user.py
djangoauthtoken/models/custom_fields/__init__.py
djangoauthtoken/models/custom_fields/case_insensitive_email_field.py
djangoauthtoken/serializers/__init__.py
djangoauthtoken/serializers/user.py
djangoauthtoken/utils/__init__.py
djangoauthtoken/utils/csrf_utils.py
djangoauthtoken/utils/datetime_utils.py
djangoauthtoken/views/__init__.py
djangoauthtoken/views/login.py
djangoauthtoken/views/refresh_token.py
djangoauthtoken/views/sign_up.py
djangoauthtoken/views/user.py
auth_token_django-0.2.5.dist-info/METADATA
auth_token_django-0.2.5.dist-info/WHEEL
auth_token_django-0.2.5.dist-info/top_level.txt
auth_token_django-0.2.5.dist-info/RECORD
